google_ads_megalista-18.0.2-py3.10-nspkg.pth
google/ads/googleads/__init__.py
google/ads/googleads/client.py
google/ads/googleads/config.py
google/ads/googleads/errors.py
google/ads/googleads/oauth2.py
google/ads/googleads/util.py
google/ads/googleads/interceptors/__init__.py
google/ads/googleads/interceptors/exception_interceptor.py
google/ads/googleads/interceptors/helpers.py
google/ads/googleads/interceptors/interceptor.py
google/ads/googleads/interceptors/logging_interceptor.py
google/ads/googleads/interceptors/metadata_interceptor.py
google/ads/googleads/interceptors/response_wrappers.py
google/ads/googleads/v13/__init__.py
google/ads/googleads/v13/common/__init__.py
google/ads/googleads/v13/common/services/__init__.py
google/ads/googleads/v13/common/types/__init__.py
google/ads/googleads/v13/common/types/ad_asset.py
google/ads/googleads/v13/common/types/ad_type_infos.py
google/ads/googleads/v13/common/types/asset_policy.py
google/ads/googleads/v13/common/types/asset_types.py
google/ads/googleads/v13/common/types/asset_usage.py
google/ads/googleads/v13/common/types/audiences.py
google/ads/googleads/v13/common/types/bidding.py
google/ads/googleads/v13/common/types/click_location.py
google/ads/googleads/v13/common/types/criteria.py
google/ads/googleads/v13/common/types/criterion_category_availability.py
google/ads/googleads/v13/common/types/custom_parameter.py
google/ads/googleads/v13/common/types/customizer_value.py
google/ads/googleads/v13/common/types/dates.py
google/ads/googleads/v13/common/types/explorer_auto_optimizer_setting.py
google/ads/googleads/v13/common/types/extensions.py
google/ads/googleads/v13/common/types/feed_common.py
google/ads/googleads/v13/common/types/feed_item_set_filter_type_infos.py
google/ads/googleads/v13/common/types/final_app_url.py
google/ads/googleads/v13/common/types/frequency_cap.py
google/ads/googleads/v13/common/types/keyword_plan_common.py
google/ads/googleads/v13/common/types/matching_function.py
google_ads_megalista-18.0.2.dist-info/LICENSE
google_ads_megalista-18.0.2.dist-info/METADATA
google_ads_megalista-18.0.2.dist-info/WHEEL
google_ads_megalista-18.0.2.dist-info/namespace_packages.txt
google_ads_megalista-18.0.2.dist-info/top_level.txt
google_ads_megalista-18.0.2.dist-info/RECORD
