Metadata-Version: 2.1
Name: google-ads-megalista
Version: 18.0.2
Summary: Customized version of google-ads for Megalista
Home-page: https://github.com/googleads/google-ads-python
Author: Google LLC
Author-email: googleapis-packages@google.com
License: Apache 2.0
Classifier: Intended Audience :: Developers
Classifier: Development Status :: 5 - Production/Stable
Classifier: Intended Audience :: Developers
Classifier: License :: OSI Approved :: Apache Software License
Classifier: Programming Language :: Python
Classifier: Programming Language :: Python :: 3
Classifier: Programming Language :: Python :: 3.7
Requires-Python: >=3.7
License-File: LICENSE
Requires-Dist: google-auth-oauthlib (<1.0.0,>=0.3.0)
Requires-Dist: google-api-core (!=2.0.*,!=2.1.*,!=2.2.*,!=2.3.0,<3.0.0dev,>=2.8.1)
Requires-Dist: googleapis-common-protos (<2.0.0,>=1.5.8)
Requires-Dist: grpcio (<2.0.0,>=1.38.1)
Requires-Dist: grpcio-status (<2.0.0,>=1.38.1)
Requires-Dist: proto-plus (==1.19.6)
Requires-Dist: PyYAML (<7.0,>=5.1)
Requires-Dist: setuptools (>=40.3.0)
Requires-Dist: protobuf (!=3.18.*,!=3.19.*,<=3.20.3,>=3.12.0)
Provides-Extra: tests
Requires-Dist: nox (<2022.6,>=2020.12.31) ; extra == 'tests'
